northstar_agent/__init__.py
northstar_agent/metrics/__init__.py
northstar_agent/metrics/base.py
northstar_agent/metrics/cpu.py
northstar_agent/metrics/disk.py
northstar_agent/metrics/enums.py
northstar_agent/metrics/memory.py
northstar_agent/metrics/network.py
northstar_agent/metrics/utils.py
northstar_agent/metrics/schemas/__init__.py
northstar_agent-1.0.3.dist-info/METADATA
northstar_agent-1.0.3.dist-info/WHEEL
northstar_agent-1.0.3.dist-info/top_level.txt
northstar_agent-1.0.3.dist-info/RECORD
